{"Home Page (phazed.xyz)":[{"online":true,"code":200,"text":"OK","timestamp":1678211821557},{"online":true,"code":200,"text":"OK","timestamp":1678213111633},{"online":true,"code":200,"text":"OK","timestamp":1678214159294},{"online":true,"code":200,"text":"OK","timestamp":1678214774746},{"online":true,"code":200,"text":"OK","timestamp":1678215279375},{"online":true,"code":200,"text":"OK","timestamp":1678216099728},{"online":true,"code":200,"text":"OK","timestamp":1678216836412},{"online":true,"code":200,"text":"OK","timestamp":1678217344792},{"online":true,"code":200,"text":"OK","timestamp":1678217855596},{"online":true,"code":200,"text":"OK","timestamp":1678218362097},{"online":true,"code":200,"text":"OK","timestamp":1678218862328},{"online":true,"code":200,"text":"OK","timestamp":1678219825899},{"online":true,"code":200,"text":"OK","timestamp":1678220864917},{"online":true,"code":200,"text":"OK","timestamp":1678221461252},{"online":true,"code":200,"text":"OK","timestamp":1678221960307},{"online":true,"code":200,"text":"OK","timestamp":1678222467909},{"online":true,"code":200,"text":"OK","timestamp":1678223336928},{"online":true,"code":200,"text":"OK","timestamp":1678224269870},{"online":true,"code":200,"text":"OK","timestamp":1678224738881},{"online":true,"code":200,"text":"OK","timestamp":1678225247960},{"online":true,"code":200,"text":"OK","timestamp":1678225759504},{"online":true,"code":200,"text":"OK","timestamp":1678226252362},{"online":true,"code":200,"text":"OK","timestamp":1678227343069},{"online":true,"code":200,"text":"OK","timestamp":1678228246459},{"online":true,"code":200,"text":"OK","timestamp":1678228836171},{"online":true,"code":200,"text":"OK","timestamp":1678229347606},{"online":true,"code":200,"text":"OK","timestamp":1678229861579},{"online":true,"code":200,"text":"OK","timestamp":1678231024527},{"online":true,"code":200,"text":"OK","timestamp":1678231784677},{"online":true,"code":200,"text":"OK","timestamp":1678232340261},{"online":true,"code":200,"text":"OK","timestamp":1678232850250},{"online":true,"code":200,"text":"OK","timestamp":1678233350242},{"online":true,"code":200,"text":"OK","timestamp":1678237658729},{"online":true,"code":200,"text":"OK","timestamp":1678243005868},{"online":true,"code":200,"text":"OK","timestamp":1678244831628},{"online":true,"code":200,"text":"OK","timestamp":1678246311519},{"online":true,"code":200,"text":"OK","timestamp":1678247032252},{"online":true,"code":200,"text":"OK","timestamp":1678247536916},{"online":true,"code":200,"text":"OK","timestamp":1678248418988},{"online":true,"code":200,"text":"OK","timestamp":1678249794946},{"online":true,"code":200,"text":"OK","timestamp":1678250614199},{"online":true,"code":200,"text":"OK","timestamp":1678251122388},{"online":true,"code":200,"text":"OK","timestamp":1678251644970},{"online":true,"code":200,"text":"OK","timestamp":1678252843577},{"online":true,"code":200,"text":"OK","timestamp":1678253451075},{"online":true,"code":200,"text":"OK","timestamp":1678253944565},{"online":true,"code":200,"text":"OK","timestamp":1678254459437},{"online":true,"code":200,"text":"OK","timestamp":1678254977534},{"online":true,"code":200,"text":"OK","timestamp":1678256252681},{"online":true,"code":200,"text":"OK","timestamp":1678257341636},{"online":true,"code":200,"text":"OK","timestamp":1678257963871},{"online":true,"code":200,"text":"OK","timestamp":1678258470067},{"online":true,"code":200,"text":"OK","timestamp":1678259346165},{"online":true,"code":200,"text":"OK","timestamp":1678260190674},{"online":true,"code":200,"text":"OK","timestamp":1678260712552},{"online":true,"code":200,"text":"OK","timestamp":1678261229110},{"online":true,"code":200,"text":"OK","timestamp":1678261737715},{"online":true,"code":200,"text":"OK","timestamp":1678262237944},{"online":true,"code":200,"text":"OK","timestamp":1678263609913},{"online":true,"code":200,"text":"OK","timestamp":1678264642442},{"online":true,"code":200,"text":"OK","timestamp":1678265217612},{"online":true,"code":200,"text":"OK","timestamp":1678265723534},{"online":true,"code":200,"text":"OK","timestamp":1678266725648},{"online":true,"code":200,"text":"OK","timestamp":1678267640038},{"online":true,"code":200,"text":"OK","timestamp":1678268207457},{"online":true,"code":200,"text":"OK","timestamp":1678268710524},{"online":true,"code":200,"text":"OK","timestamp":1678269229836},{"online":true,"code":200,"text":"OK","timestamp":1678270169683},{"online":true,"code":200,"text":"OK","timestamp":1678271421204},{"online":true,"code":200,"text":"OK","timestamp":1678272124501},{"online":true,"code":200,"text":"OK","timestamp":1678272632392},{"online":true,"code":200,"text":"OK","timestamp":1678273129474},{"online":true,"code":200,"text":"OK","timestamp":1678274149199},{"online":true,"code":200,"text":"OK","timestamp":1678274735359},{"online":true,"code":200,"text":"OK","timestamp":1678275299062},{"online":true,"code":200,"text":"OK","timestamp":1678275812143},{"online":true,"code":200,"text":"OK","timestamp":1678276319747},{"online":true,"code":200,"text":"OK","timestamp":1678276830448},{"online":true,"code":200,"text":"OK","timestamp":1678279296451},{"online":true,"code":200,"text":"OK","timestamp":1678280733907},{"online":true,"code":200,"text":"OK","timestamp":1678282255234},{"online":true,"code":200,"text":"OK","timestamp":1678282895003},{"online":true,"code":200,"text":"OK","timestamp":1678283395596},{"online":true,"code":200,"text":"OK","timestamp":1678283901337},{"online":true,"code":200,"text":"OK","timestamp":1678285005638},{"online":true,"code":200,"text":"OK","timestamp":1678285840738},{"online":true,"code":200,"text":"OK","timestamp":1678286450328},{"online":true,"code":200,"text":"OK","timestamp":1678286957878},{"online":true,"code":200,"text":"OK","timestamp":1678287458299},{"online":true,"code":200,"text":"OK","timestamp":1678288652818},{"online":true,"code":200,"text":"OK","timestamp":1678289515516},{"online":true,"code":200,"text":"OK","timestamp":1678290130561},{"online":true,"code":200,"text":"OK","timestamp":1678290641095},{"online":true,"code":200,"text":"OK","timestamp":1678291145616},{"online":true,"code":200,"text":"OK","timestamp":1678292826916},{"online":true,"code":200,"text":"OK","timestamp":1678294064340},{"online":true,"code":200,"text":"OK","timestamp":1678294603462},{"online":true,"code":200,"text":"OK","timestamp":1678295584277},{"online":true,"code":200,"text":"OK","timestamp":1678296513864},{"online":true,"code":200,"text":"OK","timestamp":1678297081856},{"online":true,"code":200,"text":"OK","timestamp":1678297589242}],"Proxy Server":[{"online":true,"code":200,"text":"OK","timestamp":1678211821914},{"online":true,"code":200,"text":"OK","timestamp":1678213111911},{"online":true,"code":200,"text":"OK","timestamp":1678214159600},{"online":true,"code":200,"text":"OK","timestamp":1678214774920},{"online":true,"code":200,"text":"OK","timestamp":1678215279640},{"online":true,"code":200,"text":"OK","timestamp":1678216100046},{"online":true,"code":200,"text":"OK","timestamp":1678216836565},{"online":true,"code":200,"text":"OK","timestamp":1678217344943},{"online":true,"code":200,"text":"OK","timestamp":1678217855744},{"online":true,"code":200,"text":"OK","timestamp":1678218362433},{"online":true,"code":200,"text":"OK","timestamp":1678218862477},{"online":true,"code":200,"text":"OK","timestamp":1678219826246},{"online":true,"code":200,"text":"OK","timestamp":1678220865235},{"online":true,"code":200,"text":"OK","timestamp":1678221461389},{"online":true,"code":200,"text":"OK","timestamp":1678221960585},{"online":true,"code":200,"text":"OK","timestamp":1678222468046},{"online":true,"code":200,"text":"OK","timestamp":1678223337068},{"online":true,"code":200,"text":"OK","timestamp":1678224270010},{"online":true,"code":200,"text":"OK","timestamp":1678224739029},{"online":true,"code":200,"text":"OK","timestamp":1678225248088},{"online":true,"code":200,"text":"OK","timestamp":1678225759654},{"online":true,"code":200,"text":"OK","timestamp":1678226252760},{"online":true,"code":200,"text":"OK","timestamp":1678227343431},{"online":true,"code":200,"text":"OK","timestamp":1678228246741},{"online":true,"code":200,"text":"OK","timestamp":1678228836491},{"online":true,"code":200,"text":"OK","timestamp":1678229347747},{"online":true,"code":200,"text":"OK","timestamp":1678229861885},{"online":true,"code":200,"text":"OK","timestamp":1678231024840},{"online":true,"code":200,"text":"OK","timestamp":1678231784838},{"online":true,"code":200,"text":"OK","timestamp":1678232340585},{"online":true,"code":200,"text":"OK","timestamp":1678232850571},{"online":true,"code":200,"text":"OK","timestamp":1678233350374},{"online":true,"code":200,"text":"OK","timestamp":1678237658893},{"online":true,"code":200,"text":"OK","timestamp":1678243006028},{"online":true,"code":200,"text":"OK","timestamp":1678244831782},{"online":true,"code":200,"text":"OK","timestamp":1678246311664},{"online":true,"code":200,"text":"OK","timestamp":1678247032603},{"online":true,"code":200,"text":"OK","timestamp":1678247537235},{"online":true,"code":200,"text":"OK","timestamp":1678248419125},{"online":true,"code":200,"text":"OK","timestamp":1678249795105},{"online":true,"code":200,"text":"OK","timestamp":1678250614338},{"online":true,"code":200,"text":"OK","timestamp":1678251122521},{"online":true,"code":200,"text":"OK","timestamp":1678251645261},{"online":true,"code":200,"text":"OK","timestamp":1678252843944},{"online":true,"code":200,"text":"OK","timestamp":1678253451204},{"online":true,"code":200,"text":"OK","timestamp":1678253944903},{"online":true,"code":200,"text":"OK","timestamp":1678254459751},{"online":true,"code":200,"text":"OK","timestamp":1678254977661},{"online":true,"code":200,"text":"OK","timestamp":1678256252933},{"online":true,"code":200,"text":"OK","timestamp":1678257342198},{"online":true,"code":200,"text":"OK","timestamp":1678257964009},{"online":true,"code":200,"text":"OK","timestamp":1678258470213},{"online":true,"code":200,"text":"OK","timestamp":1678259346488},{"online":true,"code":200,"text":"OK","timestamp":1678260190956},{"online":true,"code":200,"text":"OK","timestamp":1678260712694},{"online":true,"code":200,"text":"OK","timestamp":1678261229433},{"online":true,"code":200,"text":"OK","timestamp":1678261737965},{"online":true,"code":200,"text":"OK","timestamp":1678262238078},{"online":true,"code":200,"text":"OK","timestamp":1678263610296},{"online":true,"code":200,"text":"OK","timestamp":1678264642715},{"online":true,"code":200,"text":"OK","timestamp":1678265217924},{"online":true,"code":200,"text":"OK","timestamp":1678265723865},{"online":true,"code":200,"text":"OK","timestamp":1678266725958},{"online":true,"code":200,"text":"OK","timestamp":1678267640361},{"online":true,"code":200,"text":"OK","timestamp":1678268207695},{"online":true,"code":200,"text":"OK","timestamp":1678268710659},{"online":true,"code":200,"text":"OK","timestamp":1678269230165},{"online":true,"code":200,"text":"OK","timestamp":1678270169966},{"online":true,"code":200,"text":"OK","timestamp":1678271421467},{"online":true,"code":200,"text":"OK","timestamp":1678272124644},{"online":true,"code":200,"text":"OK","timestamp":1678272632651},{"online":true,"code":200,"text":"OK","timestamp":1678273129634},{"online":true,"code":200,"text":"OK","timestamp":1678274149528},{"online":true,"code":200,"text":"OK","timestamp":1678274735690},{"online":true,"code":200,"text":"OK","timestamp":1678275299377},{"online":true,"code":200,"text":"OK","timestamp":1678275812264},{"online":true,"code":200,"text":"OK","timestamp":1678276319891},{"online":true,"code":200,"text":"OK","timestamp":1678276830759},{"online":true,"code":200,"text":"OK","timestamp":1678279296745},{"online":true,"code":200,"text":"OK","timestamp":1678280734037},{"online":true,"code":200,"text":"OK","timestamp":1678282255383},{"online":true,"code":200,"text":"OK","timestamp":1678282895253},{"online":true,"code":200,"text":"OK","timestamp":1678283395927},{"online":true,"code":200,"text":"OK","timestamp":1678283901658},{"online":true,"code":200,"text":"OK","timestamp":1678285005777},{"online":true,"code":200,"text":"OK","timestamp":1678285841008},{"online":true,"code":200,"text":"OK","timestamp":1678286450451},{"online":true,"code":200,"text":"OK","timestamp":1678286958023},{"online":true,"code":200,"text":"OK","timestamp":1678287458561},{"online":true,"code":200,"text":"OK","timestamp":1678288652958},{"online":true,"code":200,"text":"OK","timestamp":1678289515934},{"online":true,"code":200,"text":"OK","timestamp":1678290130843},{"online":true,"code":200,"text":"OK","timestamp":1678290641376},{"online":true,"code":200,"text":"OK","timestamp":1678291145931},{"online":true,"code":200,"text":"OK","timestamp":1678292827366},{"online":true,"code":200,"text":"OK","timestamp":1678294064502},{"online":true,"code":200,"text":"OK","timestamp":1678294603616},{"online":true,"code":200,"text":"OK","timestamp":1678295584560},{"online":true,"code":200,"text":"OK","timestamp":1678296514140},{"online":true,"code":200,"text":"OK","timestamp":1678297082194},{"online":true,"code":200,"text":"OK","timestamp":1678297589491}],"File Sea (webstatic-sea.phazed.xyz)":[{"online":true,"code":200,"text":"OK","timestamp":1678211822403},{"online":true,"code":200,"text":"OK","timestamp":1678213112411},{"online":true,"code":200,"text":"OK","timestamp":1678214160242},{"online":true,"code":200,"text":"OK","timestamp":1678214775224},{"online":true,"code":200,"text":"OK","timestamp":1678215280165},{"online":true,"code":200,"text":"OK","timestamp":1678216100705},{"online":true,"code":200,"text":"OK","timestamp":1678216836820},{"online":true,"code":200,"text":"OK","timestamp":1678217345220},{"online":true,"code":200,"text":"OK","timestamp":1678217856010},{"online":true,"code":200,"text":"OK","timestamp":1678218363057},{"online":true,"code":200,"text":"OK","timestamp":1678218862745},{"online":true,"code":200,"text":"OK","timestamp":1678219826911},{"online":true,"code":200,"text":"OK","timestamp":1678220865878},{"online":true,"code":200,"text":"OK","timestamp":1678221461684},{"online":true,"code":200,"text":"OK","timestamp":1678221960948},{"online":true,"code":200,"text":"OK","timestamp":1678222468319},{"online":true,"code":200,"text":"OK","timestamp":1678223337354},{"online":true,"code":200,"text":"OK","timestamp":1678224270274},{"online":true,"code":200,"text":"OK","timestamp":1678224739313},{"online":true,"code":200,"text":"OK","timestamp":1678225248365},{"online":true,"code":200,"text":"OK","timestamp":1678225759916},{"online":true,"code":200,"text":"OK","timestamp":1678226253270},{"online":true,"code":200,"text":"OK","timestamp":1678227344153},{"online":true,"code":200,"text":"OK","timestamp":1678228247278},{"online":true,"code":200,"text":"OK","timestamp":1678228837126},{"online":true,"code":200,"text":"OK","timestamp":1678229348018},{"online":true,"code":200,"text":"OK","timestamp":1678229862333},{"online":true,"code":200,"text":"OK","timestamp":1678231025199},{"online":true,"code":200,"text":"OK","timestamp":1678231785102},{"online":true,"code":200,"text":"OK","timestamp":1678232341258},{"online":true,"code":200,"text":"OK","timestamp":1678232851222},{"online":true,"code":200,"text":"OK","timestamp":1678233350624},{"online":true,"code":200,"text":"OK","timestamp":1678237659176},{"online":true,"code":200,"text":"OK","timestamp":1678243006299},{"online":true,"code":200,"text":"OK","timestamp":1678244832055},{"online":true,"code":200,"text":"OK","timestamp":1678246311939},{"online":true,"code":200,"text":"OK","timestamp":1678247033247},{"online":true,"code":200,"text":"OK","timestamp":1678247537870},{"online":true,"code":200,"text":"OK","timestamp":1678248419406},{"online":true,"code":200,"text":"OK","timestamp":1678249795365},{"online":true,"code":200,"text":"OK","timestamp":1678250614644},{"online":true,"code":200,"text":"OK","timestamp":1678251122792},{"online":true,"code":200,"text":"OK","timestamp":1678251645775},{"online":true,"code":200,"text":"OK","timestamp":1678252844454},{"online":true,"code":200,"text":"OK","timestamp":1678253451487},{"online":true,"code":200,"text":"OK","timestamp":1678253945549},{"online":true,"code":200,"text":"OK","timestamp":1678254460406},{"online":true,"code":200,"text":"OK","timestamp":1678254977940},{"online":true,"code":200,"text":"OK","timestamp":1678256253394},{"online":true,"code":200,"text":"OK","timestamp":1678257342811},{"online":true,"code":200,"text":"OK","timestamp":1678257964306},{"online":true,"code":200,"text":"OK","timestamp":1678258470504},{"online":true,"code":200,"text":"OK","timestamp":1678259347148},{"online":true,"code":200,"text":"OK","timestamp":1678260191448},{"online":true,"code":200,"text":"OK","timestamp":1678260712945},{"online":true,"code":200,"text":"OK","timestamp":1678261230056},{"online":true,"code":200,"text":"OK","timestamp":1678261738446},{"online":true,"code":200,"text":"OK","timestamp":1678262238342},{"online":true,"code":200,"text":"OK","timestamp":1678263610902},{"online":true,"code":200,"text":"OK","timestamp":1678264643212},{"online":true,"code":200,"text":"OK","timestamp":1678265218543},{"online":true,"code":200,"text":"OK","timestamp":1678265724514},{"online":true,"code":200,"text":"OK","timestamp":1678266726601},{"online":true,"code":200,"text":"OK","timestamp":1678267640979},{"online":true,"code":200,"text":"OK","timestamp":1678268208146},{"online":true,"code":200,"text":"OK","timestamp":1678268710934},{"online":true,"code":200,"text":"OK","timestamp":1678269230922},{"online":true,"code":200,"text":"OK","timestamp":1678270170469},{"online":true,"code":200,"text":"OK","timestamp":1678271422084},{"online":true,"code":200,"text":"OK","timestamp":1678272124922},{"online":true,"code":200,"text":"OK","timestamp":1678272632996},{"online":true,"code":200,"text":"OK","timestamp":1678273129883},{"online":true,"code":200,"text":"OK","timestamp":1678274150177},{"online":true,"code":200,"text":"OK","timestamp":1678274736326},{"online":true,"code":200,"text":"OK","timestamp":1678275300000},{"online":true,"code":200,"text":"OK","timestamp":1678275812542},{"online":true,"code":200,"text":"OK","timestamp":1678276320421},{"online":true,"code":200,"text":"OK","timestamp":1678276831408},{"online":true,"code":200,"text":"OK","timestamp":1678279297249},{"online":true,"code":200,"text":"OK","timestamp":1678280734334},{"online":true,"code":200,"text":"OK","timestamp":1678282255661},{"online":true,"code":200,"text":"OK","timestamp":1678282895733},{"online":true,"code":200,"text":"OK","timestamp":1678283396598},{"online":true,"code":200,"text":"OK","timestamp":1678283902312},{"online":true,"code":200,"text":"OK","timestamp":1678285006047},{"online":true,"code":200,"text":"OK","timestamp":1678285841522},{"online":true,"code":200,"text":"OK","timestamp":1678286450727},{"online":true,"code":200,"text":"OK","timestamp":1678286958288},{"online":true,"code":200,"text":"OK","timestamp":1678287459054},{"online":true,"code":200,"text":"OK","timestamp":1678288653249},{"online":true,"code":200,"text":"OK","timestamp":1678289516416},{"online":true,"code":200,"text":"OK","timestamp":1678290131356},{"online":true,"code":200,"text":"OK","timestamp":1678290641870},{"online":true,"code":200,"text":"OK","timestamp":1678291146586},{"online":true,"code":200,"text":"OK","timestamp":1678292828021},{"online":true,"code":200,"text":"OK","timestamp":1678294064768},{"online":true,"code":200,"text":"OK","timestamp":1678294603903},{"online":true,"code":200,"text":"OK","timestamp":1678295585077},{"online":true,"code":200,"text":"OK","timestamp":1678296514445},{"online":true,"code":200,"text":"OK","timestamp":1678297082815},{"online":true,"code":200,"text":"OK","timestamp":1678297589981}],"UK National Grid Monitor (grid.phazed.xyz)":[{"online":true,"code":200,"text":"OK","timestamp":1678211822659},{"online":true,"code":200,"text":"OK","timestamp":1678213112666},{"online":true,"code":200,"text":"OK","timestamp":1678214160535},{"online":true,"code":200,"text":"OK","timestamp":1678214775388},{"online":true,"code":200,"text":"OK","timestamp":1678215280429},{"online":true,"code":200,"text":"OK","timestamp":1678216100995},{"online":true,"code":200,"text":"OK","timestamp":1678216836953},{"online":true,"code":200,"text":"OK","timestamp":1678217345352},{"online":true,"code":200,"text":"OK","timestamp":1678217856163},{"online":true,"code":200,"text":"OK","timestamp":1678218363371},{"online":true,"code":200,"text":"OK","timestamp":1678218862870},{"online":true,"code":200,"text":"OK","timestamp":1678219827238},{"online":true,"code":200,"text":"OK","timestamp":1678220866305},{"online":true,"code":200,"text":"OK","timestamp":1678221461803},{"online":true,"code":200,"text":"OK","timestamp":1678221961223},{"online":true,"code":200,"text":"OK","timestamp":1678222468465},{"online":true,"code":200,"text":"OK","timestamp":1678223337486},{"online":true,"code":200,"text":"OK","timestamp":1678224270408},{"online":true,"code":200,"text":"OK","timestamp":1678224739453},{"online":true,"code":200,"text":"OK","timestamp":1678225248474},{"online":true,"code":200,"text":"OK","timestamp":1678225760032},{"online":true,"code":200,"text":"OK","timestamp":1678226253541},{"online":true,"code":200,"text":"OK","timestamp":1678227344459},{"online":true,"code":200,"text":"OK","timestamp":1678228247550},{"online":true,"code":200,"text":"OK","timestamp":1678228837420},{"online":true,"code":200,"text":"OK","timestamp":1678229348141},{"online":true,"code":200,"text":"OK","timestamp":1678229862624},{"online":true,"code":200,"text":"OK","timestamp":1678231025411},{"online":true,"code":200,"text":"OK","timestamp":1678231785222},{"online":true,"code":200,"text":"OK","timestamp":1678232341588},{"online":true,"code":200,"text":"OK","timestamp":1678232851529},{"online":true,"code":200,"text":"OK","timestamp":1678233350738},{"online":true,"code":200,"text":"OK","timestamp":1678237659312},{"online":true,"code":200,"text":"OK","timestamp":1678243006419},{"online":true,"code":200,"text":"OK","timestamp":1678244832192},{"online":true,"code":200,"text":"OK","timestamp":1678246312064},{"online":true,"code":200,"text":"OK","timestamp":1678247033567},{"online":true,"code":200,"text":"OK","timestamp":1678247538170},{"online":true,"code":200,"text":"OK","timestamp":1678248419547},{"online":true,"code":200,"text":"OK","timestamp":1678249795478},{"online":true,"code":200,"text":"OK","timestamp":1678250614782},{"online":true,"code":200,"text":"OK","timestamp":1678251122952},{"online":true,"code":200,"text":"OK","timestamp":1678251646032},{"online":true,"code":200,"text":"OK","timestamp":1678252844727},{"online":true,"code":200,"text":"OK","timestamp":1678253451618},{"online":true,"code":200,"text":"OK","timestamp":1678253945865},{"online":true,"code":200,"text":"OK","timestamp":1678254460726},{"online":true,"code":200,"text":"OK","timestamp":1678254978071},{"online":true,"code":200,"text":"OK","timestamp":1678256253640},{"online":true,"code":200,"text":"OK","timestamp":1678257343114},{"online":true,"code":200,"text":"OK","timestamp":1678257964427},{"online":true,"code":200,"text":"OK","timestamp":1678258470663},{"online":true,"code":200,"text":"OK","timestamp":1678259347482},{"online":true,"code":200,"text":"OK","timestamp":1678260191704},{"online":true,"code":200,"text":"OK","timestamp":1678260713066},{"online":true,"code":200,"text":"OK","timestamp":1678261230345},{"online":true,"code":200,"text":"OK","timestamp":1678261738680},{"online":true,"code":200,"text":"OK","timestamp":1678262238462},{"online":true,"code":200,"text":"OK","timestamp":1678263611196},{"online":true,"code":200,"text":"OK","timestamp":1678264643478},{"online":true,"code":200,"text":"OK","timestamp":1678265218845},{"online":true,"code":200,"text":"OK","timestamp":1678265724836},{"online":true,"code":200,"text":"OK","timestamp":1678266726906},{"online":true,"code":200,"text":"OK","timestamp":1678267641280},{"online":true,"code":200,"text":"OK","timestamp":1678268208379},{"online":true,"code":200,"text":"OK","timestamp":1678268711055},{"online":true,"code":200,"text":"OK","timestamp":1678269231251},{"online":true,"code":200,"text":"OK","timestamp":1678270170728},{"online":true,"code":200,"text":"OK","timestamp":1678271422327},{"online":true,"code":200,"text":"OK","timestamp":1678272125051},{"online":true,"code":200,"text":"OK","timestamp":1678272633211},{"online":true,"code":200,"text":"OK","timestamp":1678273130002},{"online":true,"code":200,"text":"OK","timestamp":1678274150493},{"online":true,"code":200,"text":"OK","timestamp":1678274736632},{"online":true,"code":200,"text":"OK","timestamp":1678275300288},{"online":true,"code":200,"text":"OK","timestamp":1678275812660},{"online":true,"code":200,"text":"OK","timestamp":1678276320544},{"online":true,"code":200,"text":"OK","timestamp":1678276831707},{"online":true,"code":200,"text":"OK","timestamp":1678279297477},{"online":true,"code":200,"text":"OK","timestamp":1678280734462},{"online":true,"code":200,"text":"OK","timestamp":1678282255771},{"online":true,"code":200,"text":"OK","timestamp":1678282895955},{"online":true,"code":200,"text":"OK","timestamp":1678283396925},{"online":true,"code":200,"text":"OK","timestamp":1678283902645},{"online":true,"code":200,"text":"OK","timestamp":1678285006180},{"online":true,"code":200,"text":"OK","timestamp":1678285841781},{"online":true,"code":200,"text":"OK","timestamp":1678286450860},{"online":true,"code":200,"text":"OK","timestamp":1678286958423},{"online":true,"code":200,"text":"OK","timestamp":1678287459312},{"online":true,"code":200,"text":"OK","timestamp":1678288653382},{"online":true,"code":200,"text":"OK","timestamp":1678289516671},{"online":true,"code":200,"text":"OK","timestamp":1678290131644},{"online":true,"code":200,"text":"OK","timestamp":1678290642115},{"online":true,"code":200,"text":"OK","timestamp":1678291146906},{"online":true,"code":200,"text":"OK","timestamp":1678292828310},{"online":true,"code":200,"text":"OK","timestamp":1678294064885},{"online":true,"code":200,"text":"OK","timestamp":1678294604020},{"online":true,"code":200,"text":"OK","timestamp":1678295585328},{"online":true,"code":200,"text":"OK","timestamp":1678296514579},{"online":true,"code":200,"text":"OK","timestamp":1678297083119},{"online":true,"code":200,"text":"OK","timestamp":1678297590221}],"Cynosure Home (c.phazed.xyz)":[{"online":true,"code":200,"text":"OK","timestamp":1678211822904},{"online":true,"code":200,"text":"OK","timestamp":1678213112942},{"online":true,"code":200,"text":"OK","timestamp":1678214160860},{"online":true,"code":200,"text":"OK","timestamp":1678214775550},{"online":true,"code":200,"text":"OK","timestamp":1678215280703},{"online":true,"code":200,"text":"OK","timestamp":1678216101315},{"online":true,"code":200,"text":"OK","timestamp":1678216837183},{"online":true,"code":200,"text":"OK","timestamp":1678217345495},{"online":true,"code":200,"text":"OK","timestamp":1678217856287},{"online":true,"code":200,"text":"OK","timestamp":1678218363690},{"online":true,"code":200,"text":"OK","timestamp":1678218862998},{"online":true,"code":200,"text":"OK","timestamp":1678219827599},{"online":true,"code":200,"text":"OK","timestamp":1678220866641},{"online":true,"code":200,"text":"OK","timestamp":1678221461945},{"online":true,"code":200,"text":"OK","timestamp":1678221961469},{"online":true,"code":200,"text":"OK","timestamp":1678222468590},{"online":true,"code":200,"text":"OK","timestamp":1678223337621},{"online":true,"code":200,"text":"OK","timestamp":1678224270557},{"online":true,"code":200,"text":"OK","timestamp":1678224739593},{"online":true,"code":200,"text":"OK","timestamp":1678225248593},{"online":true,"code":200,"text":"OK","timestamp":1678225760168},{"online":true,"code":200,"text":"OK","timestamp":1678226253783},{"online":true,"code":200,"text":"OK","timestamp":1678227344780},{"online":true,"code":200,"text":"OK","timestamp":1678228247849},{"online":true,"code":200,"text":"OK","timestamp":1678228837743},{"online":true,"code":200,"text":"OK","timestamp":1678229348300},{"online":true,"code":200,"text":"OK","timestamp":1678229862887},{"online":true,"code":200,"text":"OK","timestamp":1678231025682},{"online":true,"code":200,"text":"OK","timestamp":1678231785366},{"online":true,"code":200,"text":"OK","timestamp":1678232341952},{"online":true,"code":200,"text":"OK","timestamp":1678232851864},{"online":true,"code":200,"text":"OK","timestamp":1678233350862},{"online":true,"code":200,"text":"OK","timestamp":1678237659472},{"online":true,"code":200,"text":"OK","timestamp":1678243006556},{"online":true,"code":200,"text":"OK","timestamp":1678244832330},{"online":true,"code":200,"text":"OK","timestamp":1678246312216},{"online":true,"code":200,"text":"OK","timestamp":1678247033899},{"online":true,"code":200,"text":"OK","timestamp":1678247538519},{"online":true,"code":200,"text":"OK","timestamp":1678248419674},{"online":true,"code":200,"text":"OK","timestamp":1678249795608},{"online":true,"code":200,"text":"OK","timestamp":1678250614921},{"online":true,"code":200,"text":"OK","timestamp":1678251123086},{"online":true,"code":200,"text":"OK","timestamp":1678251646297},{"online":true,"code":200,"text":"OK","timestamp":1678252845022},{"online":true,"code":200,"text":"OK","timestamp":1678253452003},{"online":true,"code":200,"text":"OK","timestamp":1678253946201},{"online":true,"code":200,"text":"OK","timestamp":1678254461040},{"online":true,"code":200,"text":"OK","timestamp":1678254978202},{"online":true,"code":200,"text":"OK","timestamp":1678256253884},{"online":true,"code":200,"text":"OK","timestamp":1678257343433},{"online":true,"code":200,"text":"OK","timestamp":1678257964559},{"online":true,"code":200,"text":"OK","timestamp":1678258470809},{"online":true,"code":200,"text":"OK","timestamp":1678259347813},{"online":true,"code":200,"text":"OK","timestamp":1678260191981},{"online":true,"code":200,"text":"OK","timestamp":1678260713189},{"online":true,"code":200,"text":"OK","timestamp":1678261230655},{"online":true,"code":200,"text":"OK","timestamp":1678261738930},{"online":true,"code":200,"text":"OK","timestamp":1678262238584},{"online":true,"code":200,"text":"OK","timestamp":1678263611520},{"online":true,"code":200,"text":"OK","timestamp":1678264643758},{"online":true,"code":200,"text":"OK","timestamp":1678265219151},{"online":true,"code":200,"text":"OK","timestamp":1678265725175},{"online":true,"code":200,"text":"OK","timestamp":1678266727224},{"online":true,"code":200,"text":"OK","timestamp":1678267641592},{"online":true,"code":200,"text":"OK","timestamp":1678268208630},{"online":true,"code":200,"text":"OK","timestamp":1678268711190},{"online":true,"code":200,"text":"OK","timestamp":1678269231564},{"online":true,"code":200,"text":"OK","timestamp":1678270171020},{"online":true,"code":200,"text":"OK","timestamp":1678271422575},{"online":true,"code":200,"text":"OK","timestamp":1678272125193},{"online":true,"code":200,"text":"OK","timestamp":1678272633458},{"online":true,"code":200,"text":"OK","timestamp":1678273130132},{"online":true,"code":200,"text":"OK","timestamp":1678274150819},{"online":true,"code":200,"text":"OK","timestamp":1678274736951},{"online":true,"code":200,"text":"OK","timestamp":1678275300595},{"online":true,"code":200,"text":"OK","timestamp":1678275812787},{"online":true,"code":200,"text":"OK","timestamp":1678276320692},{"online":true,"code":200,"text":"OK","timestamp":1678276832079},{"online":true,"code":200,"text":"OK","timestamp":1678279297753},{"online":true,"code":200,"text":"OK","timestamp":1678280734594},{"online":true,"code":200,"text":"OK","timestamp":1678282255933},{"online":true,"code":200,"text":"OK","timestamp":1678282896227},{"online":true,"code":200,"text":"OK","timestamp":1678283397251},{"online":true,"code":200,"text":"OK","timestamp":1678283902961},{"online":true,"code":200,"text":"OK","timestamp":1678285006407},{"online":true,"code":200,"text":"OK","timestamp":1678285842042},{"online":true,"code":200,"text":"OK","timestamp":1678286450988},{"online":true,"code":200,"text":"OK","timestamp":1678286958557},{"online":true,"code":200,"text":"OK","timestamp":1678287459575},{"online":true,"code":200,"text":"OK","timestamp":1678288653519},{"online":true,"code":200,"text":"OK","timestamp":1678289516924},{"online":true,"code":200,"text":"OK","timestamp":1678290131925},{"online":true,"code":200,"text":"OK","timestamp":1678290642346},{"online":true,"code":200,"text":"OK","timestamp":1678291147234},{"online":true,"code":200,"text":"OK","timestamp":1678292828632},{"online":true,"code":200,"text":"OK","timestamp":1678294065039},{"online":true,"code":200,"text":"OK","timestamp":1678294604155},{"online":true,"code":200,"text":"OK","timestamp":1678295585584},{"online":true,"code":200,"text":"OK","timestamp":1678296514725},{"online":true,"code":200,"text":"OK","timestamp":1678297083442},{"online":true,"code":200,"text":"OK","timestamp":1678297590481}]}