{"Home Page (phazed.xyz)":[{"online":true,"code":200,"text":"OK","timestamp":1650794781109},{"online":true,"code":200,"text":"OK","timestamp":1650795006753},{"online":true,"code":200,"text":"OK","timestamp":1650796667140},{"online":true,"code":200,"text":"OK","timestamp":1650797118565},{"online":true,"code":200,"text":"OK","timestamp":1650797132367},{"online":true,"code":200,"text":"OK","timestamp":1650797138561},{"online":true,"code":200,"text":"OK","timestamp":1650798211517},{"online":true,"code":200,"text":"OK","timestamp":1650799883902},{"online":true,"code":200,"text":"OK","timestamp":1650802181593},{"online":true,"code":200,"text":"OK","timestamp":1650804866633},{"online":true,"code":200,"text":"OK","timestamp":1650806175252},{"online":true,"code":200,"text":"OK","timestamp":1650807569358},{"online":true,"code":200,"text":"OK","timestamp":1650809116729},{"online":true,"code":200,"text":"OK","timestamp":1650810786750},{"online":true,"code":200,"text":"OK","timestamp":1650812723851},{"online":true,"code":200,"text":"OK","timestamp":1650814692365},{"online":true,"code":200,"text":"OK","timestamp":1650816425510},{"online":true,"code":200,"text":"OK","timestamp":1650819058538},{"online":true,"code":200,"text":"OK","timestamp":1650820142999},{"online":true,"code":200,"text":"OK","timestamp":1650821796071},{"online":true,"code":200,"text":"OK","timestamp":1650823626829},{"online":true,"code":200,"text":"OK","timestamp":1650825635836},{"online":true,"code":200,"text":"OK","timestamp":1650827023426},{"online":true,"code":200,"text":"OK","timestamp":1650828661282},{"online":true,"code":200,"text":"OK","timestamp":1650830833264},{"online":true,"code":200,"text":"OK","timestamp":1650832569352},{"online":true,"code":200,"text":"OK","timestamp":1650834233222},{"online":true,"code":200,"text":"OK","timestamp":1650836007612},{"online":true,"code":200,"text":"OK","timestamp":1650837862017},{"online":true,"code":200,"text":"OK","timestamp":1650839760642},{"online":true,"code":200,"text":"OK","timestamp":1650841505625},{"online":true,"code":200,"text":"OK","timestamp":1650843316651},{"online":true,"code":200,"text":"OK","timestamp":1650846464745},{"online":true,"code":200,"text":"OK","timestamp":1650853593306},{"online":true,"code":200,"text":"OK","timestamp":1650857358154},{"online":true,"code":200,"text":"OK","timestamp":1650859062024},{"online":true,"code":200,"text":"OK","timestamp":1650860356766},{"online":true,"code":200,"text":"OK","timestamp":1650862139323},{"online":true,"code":200,"text":"OK","timestamp":1650863297374},{"online":true,"code":200,"text":"OK","timestamp":1650864876287},{"online":true,"code":200,"text":"OK","timestamp":1650866924363},{"online":true,"code":200,"text":"OK","timestamp":1650869114589},{"online":true,"code":200,"text":"OK","timestamp":1650870407386},{"online":true,"code":200,"text":"OK","timestamp":1650872105443},{"online":true,"code":200,"text":"OK","timestamp":1650874124369},{"online":true,"code":200,"text":"OK","timestamp":1650876168681},{"online":true,"code":200,"text":"OK","timestamp":1650877594205},{"online":true,"code":200,"text":"OK","timestamp":1650879423361},{"online":true,"code":200,"text":"OK","timestamp":1650881217175},{"online":true,"code":200,"text":"OK","timestamp":1650883200592},{"online":true,"code":200,"text":"OK","timestamp":1650884707061},{"online":true,"code":200,"text":"OK","timestamp":1650886383747},{"online":true,"code":200,"text":"OK","timestamp":1650888654983},{"online":true,"code":200,"text":"OK","timestamp":1650891661033},{"online":true,"code":200,"text":"OK","timestamp":1650894319674},{"online":true,"code":200,"text":"OK","timestamp":1650895572338},{"online":true,"code":200,"text":"OK","timestamp":1650897284930},{"online":true,"code":200,"text":"OK","timestamp":1650899236034},{"online":true,"code":200,"text":"OK","timestamp":1650901265696},{"online":true,"code":200,"text":"OK","timestamp":1650902824863},{"online":true,"code":200,"text":"OK","timestamp":1650905697277},{"online":true,"code":200,"text":"OK","timestamp":1650906777203},{"online":true,"code":200,"text":"OK","timestamp":1650908430183},{"online":true,"code":200,"text":"OK","timestamp":1650910044054},{"online":true,"code":200,"text":"OK","timestamp":1650912347280},{"online":true,"code":200,"text":"OK","timestamp":1650913427335},{"online":true,"code":200,"text":"OK","timestamp":1650915079462},{"online":true,"code":200,"text":"OK","timestamp":1650917200911},{"online":true,"code":200,"text":"OK","timestamp":1650918993094},{"online":true,"code":200,"text":"OK","timestamp":1650920719549},{"online":true,"code":200,"text":"OK","timestamp":1650922424169},{"online":true,"code":200,"text":"OK","timestamp":1650924375255},{"online":true,"code":200,"text":"OK","timestamp":1650926216716},{"online":true,"code":200,"text":"OK","timestamp":1650927982731},{"online":true,"code":200,"text":"OK","timestamp":1650929834425},{"online":true,"code":200,"text":"OK","timestamp":1650933161466},{"online":true,"code":200,"text":"OK","timestamp":1650941607282},{"online":true,"code":200,"text":"OK","timestamp":1650944465288},{"online":true,"code":200,"text":"OK","timestamp":1650946645850},{"online":true,"code":200,"text":"OK","timestamp":1650948746726},{"online":true,"code":200,"text":"OK","timestamp":1650949832360},{"online":true,"code":200,"text":"OK","timestamp":1650951379785},{"online":true,"code":200,"text":"OK","timestamp":1650953280649},{"online":true,"code":200,"text":"OK","timestamp":1650955440046}],"Proxy Server":[{"online":true,"code":200,"text":"OK","timestamp":1650794781282},{"online":true,"code":200,"text":"OK","timestamp":1650795007135},{"online":true,"code":200,"text":"OK","timestamp":1650796667305},{"online":true,"code":200,"text":"OK","timestamp":1650797118925},{"online":true,"code":200,"text":"OK","timestamp":1650797132739},{"online":true,"code":200,"text":"OK","timestamp":1650797138924},{"online":true,"code":200,"text":"OK","timestamp":1650798211680},{"online":true,"code":200,"text":"OK","timestamp":1650799884053},{"online":true,"code":200,"text":"OK","timestamp":1650802181791},{"online":true,"code":200,"text":"OK","timestamp":1650804866811},{"online":true,"code":200,"text":"OK","timestamp":1650806175439},{"online":true,"code":200,"text":"OK","timestamp":1650807569573},{"online":true,"code":200,"text":"OK","timestamp":1650809116906},{"online":true,"code":200,"text":"OK","timestamp":1650810786934},{"online":true,"code":200,"text":"OK","timestamp":1650812724034},{"online":true,"code":200,"text":"OK","timestamp":1650814692540},{"online":true,"code":200,"text":"OK","timestamp":1650816425698},{"online":true,"code":200,"text":"OK","timestamp":1650819058720},{"online":true,"code":200,"text":"OK","timestamp":1650820143270},{"online":true,"code":200,"text":"OK","timestamp":1650821796262},{"online":true,"code":200,"text":"OK","timestamp":1650823626970},{"online":true,"code":200,"text":"OK","timestamp":1650825636073},{"online":true,"code":200,"text":"OK","timestamp":1650827023590},{"online":true,"code":200,"text":"OK","timestamp":1650828661458},{"online":true,"code":200,"text":"OK","timestamp":1650830833441},{"online":true,"code":200,"text":"OK","timestamp":1650832569510},{"online":true,"code":200,"text":"OK","timestamp":1650834233391},{"online":true,"code":200,"text":"OK","timestamp":1650836007796},{"online":true,"code":200,"text":"OK","timestamp":1650837862195},{"online":true,"code":200,"text":"OK","timestamp":1650839760833},{"online":true,"code":200,"text":"OK","timestamp":1650841505777},{"online":true,"code":200,"text":"OK","timestamp":1650843316814},{"online":true,"code":200,"text":"OK","timestamp":1650846464938},{"online":true,"code":200,"text":"OK","timestamp":1650853593495},{"online":true,"code":200,"text":"OK","timestamp":1650857358335},{"online":true,"code":200,"text":"OK","timestamp":1650859062205},{"online":true,"code":200,"text":"OK","timestamp":1650860356977},{"online":true,"code":200,"text":"OK","timestamp":1650862139507},{"online":true,"code":200,"text":"OK","timestamp":1650863297541},{"online":true,"code":200,"text":"OK","timestamp":1650864876435},{"online":true,"code":200,"text":"OK","timestamp":1650866924514},{"online":true,"code":200,"text":"OK","timestamp":1650869114740},{"online":true,"code":200,"text":"OK","timestamp":1650870407569},{"online":true,"code":200,"text":"OK","timestamp":1650872105637},{"online":true,"code":200,"text":"OK","timestamp":1650874124552},{"online":true,"code":200,"text":"OK","timestamp":1650876168858},{"online":true,"code":200,"text":"OK","timestamp":1650877594381},{"online":true,"code":200,"text":"OK","timestamp":1650879423595},{"online":true,"code":200,"text":"OK","timestamp":1650881217333},{"online":true,"code":200,"text":"OK","timestamp":1650883200794},{"online":true,"code":200,"text":"OK","timestamp":1650884707230},{"online":true,"code":200,"text":"OK","timestamp":1650886383916},{"online":true,"code":200,"text":"OK","timestamp":1650888655180},{"online":true,"code":200,"text":"OK","timestamp":1650891661218},{"online":true,"code":200,"text":"OK","timestamp":1650894319784},{"online":true,"code":200,"text":"OK","timestamp":1650895572605},{"online":true,"code":200,"text":"OK","timestamp":1650897285156},{"online":true,"code":200,"text":"OK","timestamp":1650899236293},{"online":true,"code":200,"text":"OK","timestamp":1650901265912},{"online":true,"code":200,"text":"OK","timestamp":1650902825066},{"online":true,"code":200,"text":"OK","timestamp":1650905697494},{"online":true,"code":200,"text":"OK","timestamp":1650906777411},{"online":true,"code":200,"text":"OK","timestamp":1650908430339},{"online":true,"code":200,"text":"OK","timestamp":1650910044251},{"online":true,"code":200,"text":"OK","timestamp":1650912347469},{"online":true,"code":200,"text":"OK","timestamp":1650913427530},{"online":true,"code":200,"text":"OK","timestamp":1650915079710},{"online":true,"code":200,"text":"OK","timestamp":1650917201108},{"online":true,"code":200,"text":"OK","timestamp":1650918993298},{"online":true,"code":200,"text":"OK","timestamp":1650920719763},{"online":true,"code":200,"text":"OK","timestamp":1650922424378},{"online":true,"code":200,"text":"OK","timestamp":1650924375447},{"online":true,"code":200,"text":"OK","timestamp":1650926216868},{"online":true,"code":200,"text":"OK","timestamp":1650927982936},{"online":true,"code":200,"text":"OK","timestamp":1650929834605},{"online":true,"code":200,"text":"OK","timestamp":1650933161656},{"online":true,"code":200,"text":"OK","timestamp":1650941607507},{"online":true,"code":200,"text":"OK","timestamp":1650944465449},{"online":true,"code":200,"text":"OK","timestamp":1650946646006},{"online":true,"code":200,"text":"OK","timestamp":1650948746931},{"online":true,"code":200,"text":"OK","timestamp":1650949832542},{"online":true,"code":200,"text":"OK","timestamp":1650951379978},{"online":true,"code":200,"text":"OK","timestamp":1650953280819},{"online":true,"code":200,"text":"OK","timestamp":1650955440233}],"File Sea (webstatic-sea.phazed.xyz)":[{"online":true,"code":200,"text":"OK","timestamp":1650797119635},{"online":true,"code":200,"text":"OK","timestamp":1650797133383},{"online":true,"code":200,"text":"OK","timestamp":1650798212064},{"online":true,"code":200,"text":"OK","timestamp":1650799884356},{"online":true,"code":200,"text":"OK","timestamp":1650802182134},{"online":true,"code":200,"text":"OK","timestamp":1650804867052},{"online":true,"code":200,"text":"OK","timestamp":1650806175800},{"online":true,"code":200,"text":"OK","timestamp":1650807569852},{"online":true,"code":200,"text":"OK","timestamp":1650809117174},{"online":true,"code":200,"text":"OK","timestamp":1650810787344},{"online":true,"code":200,"text":"OK","timestamp":1650812724422},{"online":true,"code":200,"text":"OK","timestamp":1650814692895},{"online":true,"code":200,"text":"OK","timestamp":1650816425976},{"online":true,"code":200,"text":"OK","timestamp":1650819059010},{"online":true,"code":200,"text":"OK","timestamp":1650820143631},{"online":true,"code":200,"text":"OK","timestamp":1650821796566},{"online":true,"code":200,"text":"OK","timestamp":1650823627214},{"online":true,"code":200,"text":"OK","timestamp":1650825636287},{"online":true,"code":200,"text":"OK","timestamp":1650827023866},{"online":true,"code":200,"text":"OK","timestamp":1650828661798},{"online":true,"code":200,"text":"OK","timestamp":1650830833796},{"online":true,"code":200,"text":"OK","timestamp":1650832569847},{"online":true,"code":200,"text":"OK","timestamp":1650834233596},{"online":true,"code":200,"text":"OK","timestamp":1650836008138},{"online":true,"code":200,"text":"OK","timestamp":1650837862540},{"online":true,"code":200,"text":"OK","timestamp":1650839761110},{"online":true,"code":200,"text":"OK","timestamp":1650841506004},{"online":true,"code":200,"text":"OK","timestamp":1650843317035},{"online":true,"code":200,"text":"OK","timestamp":1650846465219},{"online":true,"code":200,"text":"OK","timestamp":1650853593941},{"online":true,"code":200,"text":"OK","timestamp":1650857358673},{"online":true,"code":200,"text":"OK","timestamp":1650859062578},{"online":true,"code":200,"text":"OK","timestamp":1650860357308},{"online":true,"code":200,"text":"OK","timestamp":1650862139786},{"online":true,"code":200,"text":"OK","timestamp":1650863297858},{"online":true,"code":200,"text":"OK","timestamp":1650864876708},{"online":true,"code":200,"text":"OK","timestamp":1650866924728},{"online":true,"code":200,"text":"OK","timestamp":1650869114972},{"online":true,"code":200,"text":"OK","timestamp":1650870407887},{"online":true,"code":200,"text":"OK","timestamp":1650872106021},{"online":true,"code":200,"text":"OK","timestamp":1650874124849},{"online":true,"code":200,"text":"OK","timestamp":1650876169197},{"online":true,"code":200,"text":"OK","timestamp":1650877594738},{"online":true,"code":200,"text":"OK","timestamp":1650879423845},{"online":true,"code":200,"text":"OK","timestamp":1650881217581},{"online":true,"code":200,"text":"OK","timestamp":1650883201128},{"online":true,"code":200,"text":"OK","timestamp":1650884707564},{"online":true,"code":200,"text":"OK","timestamp":1650886384246},{"online":true,"code":200,"text":"OK","timestamp":1650888655406},{"online":true,"code":200,"text":"OK","timestamp":1650891661543},{"online":true,"code":200,"text":"OK","timestamp":1650894320055},{"online":true,"code":200,"text":"OK","timestamp":1650895572914},{"online":true,"code":200,"text":"OK","timestamp":1650897285578},{"online":true,"code":200,"text":"OK","timestamp":1650899236645},{"online":true,"code":200,"text":"OK","timestamp":1650901266301},{"online":true,"code":200,"text":"OK","timestamp":1650902825452},{"online":true,"code":200,"text":"OK","timestamp":1650905697848},{"online":true,"code":200,"text":"OK","timestamp":1650906777743},{"online":true,"code":200,"text":"OK","timestamp":1650908430588},{"online":true,"code":200,"text":"OK","timestamp":1650910044694},{"online":true,"code":200,"text":"OK","timestamp":1650912347847},{"online":true,"code":200,"text":"OK","timestamp":1650913427883},{"online":true,"code":200,"text":"OK","timestamp":1650915080074},{"online":true,"code":200,"text":"OK","timestamp":1650917201396},{"online":true,"code":200,"text":"OK","timestamp":1650918993682},{"online":true,"code":200,"text":"OK","timestamp":1650920720052},{"online":true,"code":200,"text":"OK","timestamp":1650922424670},{"online":true,"code":200,"text":"OK","timestamp":1650924375800},{"online":true,"code":200,"text":"OK","timestamp":1650926217106},{"online":true,"code":200,"text":"OK","timestamp":1650927983218},{"online":true,"code":200,"text":"OK","timestamp":1650929834899},{"online":true,"code":200,"text":"OK","timestamp":1650933162052},{"online":true,"code":200,"text":"OK","timestamp":1650941607837},{"online":true,"code":200,"text":"OK","timestamp":1650944465765},{"online":true,"code":200,"text":"OK","timestamp":1650946646330},{"online":true,"code":200,"text":"OK","timestamp":1650948747291},{"online":true,"code":200,"text":"OK","timestamp":1650949832854},{"online":true,"code":200,"text":"OK","timestamp":1650951380363},{"online":true,"code":200,"text":"OK","timestamp":1650953281111},{"online":true,"code":200,"text":"OK","timestamp":1650955440513}]}